[{"epoch":1,"Training Loss":1.076835974,"Valid. Loss":0.7257474735,"F1 score":0.3661872591,"examples_sum":2770,"Label_F1_scores":{"GN&C":0.384,"Project Organisation \/ Documentation":0.0,"Power":0.406504065,"Structure & Mechanism":0.0,"Parameter":0.1841004184,"OBDH":0.6485507246,"Cleanliness":0.0,"Quality control":0.4530551416,"Project Scope":0.128,"Telecom.":0.1963190184,"System engineering":0.1298701299,"Propulsion":0.1346153846,"Measurement":0.8441814596,"Thermal":0.0,"Safety \/ Risk (Control)":0.2222222222,"Space Environment":0.6262886598,"Nonconformity":0.0,"Materials \/ EEEs":0.4412470024,"weighted":0.3661872591},"examples":{"GN&C":177,"Project Organisation \/ Documentation":119,"Power":139,"Structure & Mechanism":176,"Parameter":153,"OBDH":202,"Cleanliness":51,"Quality control":211,"Project Scope":115,"Telecom.":142,"System engineering":137,"Propulsion":97,"Measurement":263,"Thermal":43,"Safety \/ Risk (Control)":132,"Space Environment":332,"Nonconformity":49,"Materials \/ EEEs":232,"sum":2770},"Training Time":"0:00:14","Validation Time":"0:00:01","model_key":"roberta-base","timestamp":"20260115-153006"}]