[{"epoch":1,"Training Loss":1.1145950736,"Valid. Loss":0.8114101191,"F1 score":0.4267389135,"examples_sum":2628,"Label_F1_scores":{"Power":0.4096385542,"Materials \/ EEEs":0.4615384615,"Safety \/ Risk (Control)":0.1121495327,"Structure & Mechanism":0.3056179775,"Nonconformity":0.0,"System engineering":0.4247104247,"Space Environment":0.6311970979,"Parameter":0.3085106383,"GN&C":0.1904761905,"Thermal":0.2086956522,"Measurement":0.8424437299,"Propulsion":0.0,"Telecom.":0.273381295,"Cleanliness":0.0,"Project Organisation \/ Documentation":0.1204819277,"OBDH":0.5994550409,"Project Scope":0.0,"Quality control":0.488372093,"weighted":0.4267389135},"examples":{"Power":172,"Materials \/ EEEs":134,"Safety \/ Risk (Control)":99,"Structure & Mechanism":163,"Nonconformity":58,"System engineering":121,"Space Environment":453,"Parameter":165,"GN&C":188,"Thermal":84,"Measurement":283,"Propulsion":49,"Telecom.":115,"Cleanliness":35,"Project Organisation \/ Documentation":63,"OBDH":191,"Project Scope":61,"Quality control":194,"sum":2628},"Training Time":"0:00:36","Validation Time":"0:00:06","model_key":"deberta-v3-large","timestamp":"20260115-183718"},{"epoch":2,"Training Loss":0.5794109803,"Valid. Loss":0.5971694912,"F1 score":0.6267924273,"examples_sum":2628,"Label_F1_scores":{"Power":0.6460674157,"Materials \/ EEEs":0.6097560976,"Safety \/ Risk (Control)":0.578680203,"Structure & Mechanism":0.4924012158,"Nonconformity":0.5609756098,"System engineering":0.5294117647,"Space Environment":0.6613636364,"Parameter":0.4385964912,"GN&C":0.628742515,"Thermal":0.5989847716,"Measurement":0.8939929329,"Propulsion":0.5476190476,"Telecom.":0.5153374233,"Cleanliness":0.3913043478,"Project Organisation \/ Documentation":0.34,"OBDH":0.6704225352,"Project Scope":0.55,"Quality control":0.7419354839,"weighted":0.6267924273},"examples":{"Power":172,"Materials \/ EEEs":134,"Safety \/ Risk (Control)":99,"Structure & Mechanism":163,"Nonconformity":58,"System engineering":121,"Space Environment":453,"Parameter":165,"GN&C":188,"Thermal":84,"Measurement":283,"Propulsion":49,"Telecom.":115,"Cleanliness":35,"Project Organisation \/ Documentation":63,"OBDH":191,"Project Scope":61,"Quality control":194,"sum":2628},"Training Time":"0:00:33","Validation Time":"0:00:06","model_key":"deberta-v3-large","timestamp":"20260115-183718"},{"epoch":3,"Training Loss":0.3383110547,"Valid. Loss":0.5505471205,"F1 score":0.6751883703,"examples_sum":2628,"Label_F1_scores":{"Power":0.748502994,"Materials \/ EEEs":0.7116104869,"Safety \/ Risk (Control)":0.6769230769,"Structure & Mechanism":0.5182481752,"Nonconformity":0.7079646018,"System engineering":0.5423728814,"Space Environment":0.6606451613,"Parameter":0.5078534031,"GN&C":0.6963788301,"Thermal":0.6904761905,"Measurement":0.8931698774,"Propulsion":0.4484848485,"Telecom.":0.7393364929,"Cleanliness":0.6071428571,"Project Organisation \/ Documentation":0.4117647059,"OBDH":0.6995073892,"Project Scope":0.5481481481,"Quality control":0.7532467532,"weighted":0.6751883703},"examples":{"Power":172,"Materials \/ EEEs":134,"Safety \/ Risk (Control)":99,"Structure & Mechanism":163,"Nonconformity":58,"System engineering":121,"Space Environment":453,"Parameter":165,"GN&C":188,"Thermal":84,"Measurement":283,"Propulsion":49,"Telecom.":115,"Cleanliness":35,"Project Organisation \/ Documentation":63,"OBDH":191,"Project Scope":61,"Quality control":194,"sum":2628},"Training Time":"0:00:33","Validation Time":"0:00:05","model_key":"deberta-v3-large","timestamp":"20260115-183718"},{"epoch":4,"Training Loss":0.1991406545,"Valid. Loss":0.6280934444,"F1 score":0.6668840071,"examples_sum":2628,"Label_F1_scores":{"Power":0.7580645161,"Materials \/ EEEs":0.688,"Safety \/ Risk (Control)":0.6384976526,"Structure & Mechanism":0.5527950311,"Nonconformity":0.7083333333,"System engineering":0.5192307692,"Space Environment":0.6421768707,"Parameter":0.4571428571,"GN&C":0.643533123,"Thermal":0.7314285714,"Measurement":0.9074733096,"Propulsion":0.6788990826,"Telecom.":0.6461538462,"Cleanliness":0.701754386,"Project Organisation \/ Documentation":0.4666666667,"OBDH":0.6984924623,"Project Scope":0.5454545455,"Quality control":0.7163461538,"weighted":0.6668840071},"examples":{"Power":172,"Materials \/ EEEs":134,"Safety \/ Risk (Control)":99,"Structure & Mechanism":163,"Nonconformity":58,"System engineering":121,"Space Environment":453,"Parameter":165,"GN&C":188,"Thermal":84,"Measurement":283,"Propulsion":49,"Telecom.":115,"Cleanliness":35,"Project Organisation \/ Documentation":63,"OBDH":191,"Project Scope":61,"Quality control":194,"sum":2628},"Training Time":"0:00:31","Validation Time":"0:00:05","model_key":"deberta-v3-large","timestamp":"20260115-183718"},{"epoch":5,"Training Loss":0.133408244,"Valid. Loss":0.6099374766,"F1 score":0.6771932859,"examples_sum":2628,"Label_F1_scores":{"Power":0.7635327635,"Materials \/ EEEs":0.734082397,"Safety \/ Risk (Control)":0.6600985222,"Structure & Mechanism":0.5514705882,"Nonconformity":0.7047619048,"System engineering":0.6184738956,"Space Environment":0.6600985222,"Parameter":0.4974874372,"GN&C":0.6133333333,"Thermal":0.7142857143,"Measurement":0.8931698774,"Propulsion":0.6371681416,"Telecom.":0.6666666667,"Cleanliness":0.7384615385,"Project Organisation \/ Documentation":0.4473684211,"OBDH":0.6966292135,"Project Scope":0.4936708861,"Quality control":0.7461139896,"weighted":0.6771932859},"examples":{"Power":172,"Materials \/ EEEs":134,"Safety \/ Risk (Control)":99,"Structure & Mechanism":163,"Nonconformity":58,"System engineering":121,"Space Environment":453,"Parameter":165,"GN&C":188,"Thermal":84,"Measurement":283,"Propulsion":49,"Telecom.":115,"Cleanliness":35,"Project Organisation \/ Documentation":63,"OBDH":191,"Project Scope":61,"Quality control":194,"sum":2628},"Training Time":"0:00:32","Validation Time":"0:00:05","model_key":"deberta-v3-large","timestamp":"20260115-183718"},{"epoch":6,"Training Loss":0.0789088316,"Valid. Loss":0.680330079,"F1 score":0.6741022224,"examples_sum":2628,"Label_F1_scores":{"Power":0.734375,"Materials \/ EEEs":0.6066350711,"Safety \/ Risk (Control)":0.6524064171,"Structure & Mechanism":0.6140350877,"Nonconformity":0.6972477064,"System engineering":0.6115702479,"Space Environment":0.6504723347,"Parameter":0.4326018809,"GN&C":0.6287625418,"Thermal":0.6706586826,"Measurement":0.9312169312,"Propulsion":0.7804878049,"Telecom.":0.6349206349,"Cleanliness":0.7419354839,"Project Organisation \/ Documentation":0.4748201439,"OBDH":0.7076923077,"Project Scope":0.5673758865,"Quality control":0.7411444142,"weighted":0.6741022224},"examples":{"Power":172,"Materials \/ EEEs":134,"Safety \/ Risk (Control)":99,"Structure & Mechanism":163,"Nonconformity":58,"System engineering":121,"Space Environment":453,"Parameter":165,"GN&C":188,"Thermal":84,"Measurement":283,"Propulsion":49,"Telecom.":115,"Cleanliness":35,"Project Organisation \/ Documentation":63,"OBDH":191,"Project Scope":61,"Quality control":194,"sum":2628},"Training Time":"0:00:33","Validation Time":"0:00:05","model_key":"deberta-v3-large","timestamp":"20260115-183718"},{"epoch":7,"Training Loss":0.0792936145,"Valid. Loss":0.6233227737,"F1 score":0.7009997647,"examples_sum":2628,"Label_F1_scores":{"Power":0.7514450867,"Materials \/ EEEs":0.712,"Safety \/ Risk (Control)":0.6907216495,"Structure & Mechanism":0.6253869969,"Nonconformity":0.7142857143,"System engineering":0.6083333333,"Space Environment":0.6814814815,"Parameter":0.4767123288,"GN&C":0.7138461538,"Thermal":0.6971428571,"Measurement":0.9299145299,"Propulsion":0.7865168539,"Telecom.":0.637254902,"Cleanliness":0.7419354839,"Project Organisation \/ Documentation":0.5170068027,"OBDH":0.7064935065,"Project Scope":0.5648854962,"Quality control":0.7688442211,"weighted":0.7009997647},"examples":{"Power":172,"Materials \/ EEEs":134,"Safety \/ Risk (Control)":99,"Structure & Mechanism":163,"Nonconformity":58,"System engineering":121,"Space Environment":453,"Parameter":165,"GN&C":188,"Thermal":84,"Measurement":283,"Propulsion":49,"Telecom.":115,"Cleanliness":35,"Project Organisation \/ Documentation":63,"OBDH":191,"Project Scope":61,"Quality control":194,"sum":2628},"Training Time":"0:00:32","Validation Time":"0:00:05","model_key":"deberta-v3-large","timestamp":"20260115-183718"},{"epoch":8,"Training Loss":0.0328014803,"Valid. Loss":0.7051930552,"F1 score":0.6912252252,"examples_sum":2628,"Label_F1_scores":{"Power":0.7857142857,"Materials \/ EEEs":0.7081712062,"Safety \/ Risk (Control)":0.6634146341,"Structure & Mechanism":0.595505618,"Nonconformity":0.7079646018,"System engineering":0.6209677419,"Space Environment":0.6862483311,"Parameter":0.4781491003,"GN&C":0.6984126984,"Thermal":0.7435897436,"Measurement":0.9243986254,"Propulsion":0.7428571429,"Telecom.":0.5628742515,"Cleanliness":0.7619047619,"Project Organisation \/ Documentation":0.5138888889,"OBDH":0.647826087,"Project Scope":0.5098039216,"Quality control":0.7598944591,"weighted":0.6912252252},"examples":{"Power":172,"Materials \/ EEEs":134,"Safety \/ Risk (Control)":99,"Structure & Mechanism":163,"Nonconformity":58,"System engineering":121,"Space Environment":453,"Parameter":165,"GN&C":188,"Thermal":84,"Measurement":283,"Propulsion":49,"Telecom.":115,"Cleanliness":35,"Project Organisation \/ Documentation":63,"OBDH":191,"Project Scope":61,"Quality control":194,"sum":2628},"Training Time":"0:00:32","Validation Time":"0:00:05","model_key":"deberta-v3-large","timestamp":"20260115-183718"},{"epoch":9,"Training Loss":0.0206260811,"Valid. Loss":0.7131354523,"F1 score":0.7019782742,"examples_sum":2628,"Label_F1_scores":{"Power":0.7673716012,"Materials \/ EEEs":0.6991869919,"Safety \/ Risk (Control)":0.6842105263,"Structure & Mechanism":0.6005830904,"Nonconformity":0.6842105263,"System engineering":0.6090534979,"Space Environment":0.6962190352,"Parameter":0.4663461538,"GN&C":0.7070063694,"Thermal":0.7204968944,"Measurement":0.9275862069,"Propulsion":0.7722772277,"Telecom.":0.6764705882,"Cleanliness":0.7619047619,"Project Organisation \/ Documentation":0.5030674847,"OBDH":0.7230769231,"Project Scope":0.5531914894,"Quality control":0.7524752475,"weighted":0.7019782742},"examples":{"Power":172,"Materials \/ EEEs":134,"Safety \/ Risk (Control)":99,"Structure & Mechanism":163,"Nonconformity":58,"System engineering":121,"Space Environment":453,"Parameter":165,"GN&C":188,"Thermal":84,"Measurement":283,"Propulsion":49,"Telecom.":115,"Cleanliness":35,"Project Organisation \/ Documentation":63,"OBDH":191,"Project Scope":61,"Quality control":194,"sum":2628},"Training Time":"0:00:33","Validation Time":"0:00:05","model_key":"deberta-v3-large","timestamp":"20260115-183718"}]