[{"epoch":1,"Training Loss":1.0833353269,"Valid. Loss":0.7803671695,"F1 score":0.2922700216,"examples_sum":2387,"Label_F1_scores":{"Nonconformity":0.0,"Project Organisation \/ Documentation":0.0377358491,"Structure & Mechanism":0.1686746988,"Measurement":0.7594936709,"Thermal":0.288,"Materials \/ EEEs":0.1256544503,"Cleanliness":0.0,"OBDH":0.1210191083,"Propulsion":0.0,"Power":0.5020242915,"System engineering":0.25,"GN&C":0.1384615385,"Parameter":0.4421768707,"Safety \/ Risk (Control)":0.34375,"Quality control":0.5029239766,"Telecom.":0.3745318352,"Project Scope":0.0325203252,"Space Environment":0.5911708253,"weighted":0.2922700216},"examples":{"Nonconformity":61,"Project Organisation \/ Documentation":99,"Structure & Mechanism":77,"Measurement":114,"Thermal":74,"Materials \/ EEEs":177,"Cleanliness":67,"OBDH":255,"Propulsion":106,"Power":109,"System engineering":171,"GN&C":114,"Parameter":145,"Safety \/ Risk (Control)":91,"Quality control":243,"Telecom.":136,"Project Scope":121,"Space Environment":227,"sum":2387},"Training Time":"0:00:36","Validation Time":"0:00:06","model_key":"deberta-v3-large","timestamp":"20260115-153933"},{"epoch":2,"Training Loss":0.5908385099,"Valid. Loss":0.6107004955,"F1 score":0.5256210876,"examples_sum":2387,"Label_F1_scores":{"Nonconformity":0.4444444444,"Project Organisation \/ Documentation":0.2335766423,"Structure & Mechanism":0.3474903475,"Measurement":0.7822222222,"Thermal":0.5614035088,"Materials \/ EEEs":0.5392156863,"Cleanliness":0.1643835616,"OBDH":0.6570188133,"Propulsion":0.2834645669,"Power":0.5903614458,"System engineering":0.5365853659,"GN&C":0.5795918367,"Parameter":0.5642857143,"Safety \/ Risk (Control)":0.6794871795,"Quality control":0.6844444444,"Telecom.":0.0,"Project Scope":0.544600939,"Space Environment":0.6381322957,"weighted":0.5256210876},"examples":{"Nonconformity":61,"Project Organisation \/ Documentation":99,"Structure & Mechanism":77,"Measurement":114,"Thermal":74,"Materials \/ EEEs":177,"Cleanliness":67,"OBDH":255,"Propulsion":106,"Power":109,"System engineering":171,"GN&C":114,"Parameter":145,"Safety \/ Risk (Control)":91,"Quality control":243,"Telecom.":136,"Project Scope":121,"Space Environment":227,"sum":2387},"Training Time":"0:00:32","Validation Time":"0:00:05","model_key":"deberta-v3-large","timestamp":"20260115-153933"},{"epoch":3,"Training Loss":0.3624893401,"Valid. Loss":0.543118362,"F1 score":0.5991680372,"examples_sum":2387,"Label_F1_scores":{"Nonconformity":0.5473684211,"Project Organisation \/ Documentation":0.4387755102,"Structure & Mechanism":0.4225352113,"Measurement":0.8,"Thermal":0.7746478873,"Materials \/ EEEs":0.5230769231,"Cleanliness":0.4418604651,"OBDH":0.6992125984,"Propulsion":0.5197740113,"Power":0.7076923077,"System engineering":0.5703703704,"GN&C":0.672985782,"Parameter":0.5561797753,"Safety \/ Risk (Control)":0.7142857143,"Quality control":0.7332053743,"Telecom.":0.0845070423,"Project Scope":0.6504854369,"Space Environment":0.6666666667,"weighted":0.5991680372},"examples":{"Nonconformity":61,"Project Organisation \/ Documentation":99,"Structure & Mechanism":77,"Measurement":114,"Thermal":74,"Materials \/ EEEs":177,"Cleanliness":67,"OBDH":255,"Propulsion":106,"Power":109,"System engineering":171,"GN&C":114,"Parameter":145,"Safety \/ Risk (Control)":91,"Quality control":243,"Telecom.":136,"Project Scope":121,"Space Environment":227,"sum":2387},"Training Time":"0:00:33","Validation Time":"0:00:06","model_key":"deberta-v3-large","timestamp":"20260115-153933"}]